stat_tests.py
stat_tests-0.0.0.post5.dist-info/DESCRIPTION.rst
stat_tests-0.0.0.post5.dist-info/METADATA
stat_tests-0.0.0.post5.dist-info/RECORD
stat_tests-0.0.0.post5.dist-info/WHEEL
stat_tests-0.0.0.post5.dist-info/metadata.json
stat_tests-0.0.0.post5.dist-info/top_level.txt
