Metadata-Version: 2.0
Name: stat-tests
Version: 0.0.0.post5
Summary: Easy-to-use statistical tests in Python
Home-page: https://github.com/yang-zhang/stat-tests
Author: Yang Zhang
Author-email: yang.zhang.ds@gmail.com
License: MIT
Keywords: statistics hypothesis-testing
Platform: UNKNOWN
Classifier: Development Status :: 3 - Alpha
Classifier: Intended Audience :: Developers
Classifier: Topic :: Scientific/Engineering :: Mathematics
Classifier: License :: OSI Approved :: MIT License
Classifier: Programming Language :: Python :: 2
Classifier: Programming Language :: Python :: 2.7
Classifier: Programming Language :: Python :: 3
Classifier: Programming Language :: Python :: 3.3
Classifier: Programming Language :: Python :: 3.4
Classifier: Programming Language :: Python :: 3.5
Requires-Dist: numpy
Requires-Dist: scipy
Requires-Dist: statsmodels
